genice2/.DS_Store
genice2/CIF.py
genice2/FrankKasper.py
genice2/__init__.py
genice2/alkyl.py
genice2/analice.py
genice2/cage.py
genice2/cell.py
genice2/cli/__init__.py
genice2/cli/analice.py
genice2/cli/genice.py
genice2/decorators.py
genice2/formats/.DS_Store
genice2/formats/Makefile
genice2/formats/_KG.py
genice2/formats/__init__.py
genice2/formats/_ringstat.py
genice2/formats/c.py
genice2/formats/cif.py
genice2/formats/cif2.py
genice2/formats/com.py
genice2/formats/d.py
genice2/formats/digraph.py
genice2/formats/e.py
genice2/formats/euler.py
genice2/formats/exmol.py
genice2/formats/exyz.py
genice2/formats/g.py
genice2/formats/graph.py
genice2/formats/gromacs.py
genice2/formats/m.py
genice2/formats/mdv_au.py
genice2/formats/mdview.py
genice2/formats/null.py
genice2/formats/p.py
genice2/formats/povray.py
genice2/formats/python.py
genice2/formats/q.py
genice2/formats/quaternion.py
genice2/formats/r.py
genice2/formats/raw.py
genice2/formats/rcom.py
genice2/formats/rings.py
genice2/formats/towhee.py
genice2/formats/xyz.py
genice2/formats/y.py
genice2/formats/yaplot.py
genice2/genice.py
genice2/groups/Bu.py
genice2/groups/CH3CH2CH2CH2.py
genice2/groups/__init__.py
genice2/lattices/.DS_Store
genice2/lattices/0.py
genice2/lattices/11.py
genice2/lattices/115_2_114.py
genice2/lattices/11alt.py
genice2/lattices/11i.py
genice2/lattices/12.py
genice2/lattices/12_1_11.py
genice2/lattices/13.py
genice2/lattices/14.py
genice2/lattices/144_2_7301.py
genice2/lattices/151_2_4949650.py
genice2/lattices/153_2_155471.py
genice2/lattices/16.py
genice2/lattices/17.py
genice2/lattices/176_2_5256.py
genice2/lattices/1c.py
genice2/lattices/1h.py
genice2/lattices/1h_unit.py
genice2/lattices/2.py
genice2/lattices/207_1_4435.py
genice2/lattices/2D3.py
genice2/lattices/2_2_623457.py
genice2/lattices/2d.py
genice2/lattices/3.py
genice2/lattices/4.py
genice2/lattices/4R.py
genice2/lattices/5.py
genice2/lattices/5R.py
genice2/lattices/6.py
genice2/lattices/6h.py
genice2/lattices/7.py
genice2-2.2.12.4.dist-info/LICENSE
genice2-2.2.12.4.dist-info/METADATA
genice2-2.2.12.4.dist-info/WHEEL
genice2-2.2.12.4.dist-info/entry_points.txt
genice2-2.2.12.4.dist-info/RECORD
