Metadata-Version: 2.1
Name: genice2
Version: 2.2.12.4
Summary: A Swiss army knife to generate hydrogen-disordered ice structures.
License: MIT
Author: Masakazu Matsumoto
Author-email: vitroid@gmail.com
Requires-Python: >=3.10,<4.0
Classifier: License :: OSI Approved :: MIT License
Classifier: Programming Language :: Python :: 3
Classifier: Programming Language :: Python :: 3.10
Classifier: Programming Language :: Python :: 3.11
Classifier: Programming Language :: Python :: 3.12
Requires-Dist: cycless (>=0.4.2)
Requires-Dist: deprecation (>=2.1.0,<3.0.0)
Requires-Dist: genice-core (>=1.1)
Requires-Dist: graphstat (>=0.3.3)
Requires-Dist: networkx (>=2.0.dev20160901144005)
Requires-Dist: numpy (>=2.0,<3.0)
Requires-Dist: openpyscad (>=0.5.0)
Requires-Dist: pairlist (>=0.6)
Requires-Dist: yaplotlib (>=0.1.2)
